pycsp3_scheduling/__init__.py
pycsp3_scheduling/interop.py
pycsp3_scheduling/visu.py
pycsp3_scheduling/constraints/__init__.py
pycsp3_scheduling/constraints/_pycsp3.py
pycsp3_scheduling/constraints/bounds.py
pycsp3_scheduling/constraints/chain.py
pycsp3_scheduling/constraints/cumulative.py
pycsp3_scheduling/constraints/forbidden.py
pycsp3_scheduling/constraints/grouping.py
pycsp3_scheduling/constraints/overlap.py
pycsp3_scheduling/constraints/precedence.py
pycsp3_scheduling/constraints/presence.py
pycsp3_scheduling/constraints/sequence.py
pycsp3_scheduling/expressions/__init__.py
pycsp3_scheduling/expressions/aggregate.py
pycsp3_scheduling/expressions/element.py
pycsp3_scheduling/expressions/interval_expr.py
pycsp3_scheduling/expressions/sequence_expr.py
pycsp3_scheduling/functions/__init__.py
pycsp3_scheduling/functions/cumul_functions.py
pycsp3_scheduling/functions/state_functions.py
pycsp3_scheduling/variables/__init__.py
pycsp3_scheduling/variables/interval.py
pycsp3_scheduling/variables/sequence.py
pycsp3_scheduling-0.5.0.dist-info/METADATA
pycsp3_scheduling-0.5.0.dist-info/WHEEL
pycsp3_scheduling-0.5.0.dist-info/licenses/LICENSE
pycsp3_scheduling-0.5.0.dist-info/RECORD
